datasette_mutable_downloads/__init__.py
datasette_mutable_downloads-0.1.2.dist-info/LICENSE
datasette_mutable_downloads-0.1.2.dist-info/METADATA
datasette_mutable_downloads-0.1.2.dist-info/WHEEL
datasette_mutable_downloads-0.1.2.dist-info/entry_points.txt
datasette_mutable_downloads-0.1.2.dist-info/top_level.txt
datasette_mutable_downloads-0.1.2.dist-info/RECORD
