Metadata-Version: 2.1
Name: datasette-mutable-downloads
Version: 0.1.2
Summary: Enable downloading mutable databases.
Home-page: https://github.com/cldellow/datasette-mutable-downloads
Author: Colin Dellow
License: Apache License, Version 2.0
Project-URL: Issues, https://github.com/cldellow/datasette-mutable-downloads/issues
Project-URL: CI, https://github.com/cldellow/datasette-mutable-downloads/actions
Project-URL: Changelog, https://github.com/cldellow/datasette-mutable-downloads/releases
Classifier: Framework :: Datasette
Classifier: License :: OSI Approved :: Apache Software License
Requires-Python: >=3.7
License-File: LICENSE
Requires-Dist: datasette
Provides-Extra: test
Requires-Dist: pytest ; extra == 'test'
Requires-Dist: pytest-asyncio ; extra == 'test'
Requires-Dist: pytest-watch ; extra == 'test'
